{
  "Version": "1.0",
  "ModID": "khobs_scrap_trading_old_nate",
  "Category": {
    "Chinese": null,
    "English": "Gameplay",
    "French": "Jouabilité",
    "German": "Spielablauf",
    "Italian": null,
    "Japanese": null,
    "Korean": null,
    "Polish": null,
    "Russian": null,
    "Spanish": null,
    "Taiwanese": null
  },
  "ModName": {
    "Chinese": null,
    "English": "Scrap Trading by Old Nate",
    "French": null,
    "German": null,
    "Italian": null,
    "Japanese": null,
    "Korean": null,
    "Polish": null,
    "Russian": null,
    "Spanish": null,
    "Taiwanese": null
  },
  "Description": {
    "Chinese": null,
    "English": "Old Nate can sell scrap, nice scrap and special scrap.",
    "French": null,
    "German": null,
    "Italian": null,
    "Japanese": null,
    "Korean": null,
    "Polish": null,
    "Russian": null,
    "Spanish": null,
    "Taiwanese": null
  },
  "DLCDependencies": [
    {
      "DLC": "SunkenTreasures",
      "Dependant": "required"
    }
  ],
  "CreatorName": "Khobs",
  "CreatorContact": "https://discord.com/invite/KtfWbev",
}